bheecoding/__init__.py
bheecoding/password.py
bheecoding-0.0.1.dist-info/METADATA
bheecoding-0.0.1.dist-info/WHEEL
bheecoding-0.0.1.dist-info/top_level.txt
bheecoding-0.0.1.dist-info/RECORD
