Metadata-Version: 2.1
Name: bheecoding
Version: 0.0.1
Summary: sample package
Home-page: https://github.com/nicecoding1/
Author: Banghee So
Author-email: funnysbh@gmail.com
Classifier: Programming Language :: Python :: 3
Classifier: License :: OSI Approved :: MIT License
Classifier: Operating System :: OS Independent
Requires-Python: >=3.6
